odoo/addons/stock_orderpoint_purchase_link/README.rst
odoo/addons/stock_orderpoint_purchase_link/__init__.py
odoo/addons/stock_orderpoint_purchase_link/__manifest__.py
odoo/addons/stock_orderpoint_purchase_link/i18n/fr.po
odoo/addons/stock_orderpoint_purchase_link/i18n/stock_orderpoint_purchase_link.pot
odoo/addons/stock_orderpoint_purchase_link/i18n/zh_CN.po
odoo/addons/stock_orderpoint_purchase_link/models/__init__.py
odoo/addons/stock_orderpoint_purchase_link/models/purchase_order_line.py
odoo/addons/stock_orderpoint_purchase_link/models/stock_rule.py
odoo/addons/stock_orderpoint_purchase_link/models/stock_warehouse_orderpoint.py
odoo/addons/stock_orderpoint_purchase_link/readme/CONTRIBUTORS.rst
odoo/addons/stock_orderpoint_purchase_link/readme/DESCRIPTION.rst
odoo/addons/stock_orderpoint_purchase_link/static/description/icon.png
odoo/addons/stock_orderpoint_purchase_link/static/description/index.html
odoo/addons/stock_orderpoint_purchase_link/tests/__init__.py
odoo/addons/stock_orderpoint_purchase_link/tests/test_stock_orderpoint_purchase_link.py
odoo/addons/stock_orderpoint_purchase_link/views/purchase_order_views.xml
odoo12_addon_stock_orderpoint_purchase_link-12.0.1.0.0.99.dev11.dist-info/METADATA
odoo12_addon_stock_orderpoint_purchase_link-12.0.1.0.0.99.dev11.dist-info/WHEEL
odoo12_addon_stock_orderpoint_purchase_link-12.0.1.0.0.99.dev11.dist-info/top_level.txt
odoo12_addon_stock_orderpoint_purchase_link-12.0.1.0.0.99.dev11.dist-info/RECORD
